LICENSE
MANIFEST.in
README.rst
setup.py
./doco/__init__.py
./doco/_compat.py
./doco/client.py
./doco/dialogue.py
doco/__init__.py
doco/_compat.py
doco/client.py
doco/dialogue.py
doco.egg-info/PKG-INFO
doco.egg-info/SOURCES.txt
doco.egg-info/dependency_links.txt
doco.egg-info/requires.txt
doco.egg-info/top_level.txt
doco/doco.egg-info/PKG-INFO
doco/doco.egg-info/SOURCES.txt
doco/doco.egg-info/dependency_links.txt
doco/doco.egg-info/requires.txt
doco/doco.egg-info/top_level.txt