Metadata-Version: 1.1
Name: doco
Version: 0.0.5
Summary: Client library for docomo API written in Python.
Home-page: http://github.com/heavenshell/py-doco
Author: Shinya Ohyanagi
Author-email: sohyanagi@gmail.com
License: BSD
Platform: any
Classifier: Development Status :: 4 - Beta
Classifier: Environment :: Console
Classifier: Intended Audience :: Developers
Classifier: License :: OSI Approved :: BSD License
Classifier: Operating System :: OS Independent
Classifier: Programming Language :: Python
Classifier: Topic :: Internet :: WWW/HTTP
